Workbook

Sheet Summary
A1: DELL - Dell Technologies Inc.: LBO Returns Summary
A2: Live formulas reference each scenario sheet — edit inputs there to flex.
A4: Scenario | B4: IRR (%) | C4: MOIC | D4: Exit Equity ($M) | E4: Exit EV ($M)
A5: Base | B5: ='Base Case'!B44 | C5: ='Base Case'!B43 | D5: ='Base Case'!B42 | E5: ='Base Case'!B40
A6: Bull | B6: ='Bull Case'!B44 | C6: ='Bull Case'!B43 | D6: ='Bull Case'!B42 | E6: ='Bull Case'!B40
A7: Bear | B7: ='Bear Case'!B44 | C7: ='Bear Case'!B43 | D7: ='Bear Case'!B42 | E7: ='Bear Case'!B40

Sheet Base Case
A1: BASE CASE - LIVE LBO MODEL
A3: BLUE = hardcoded input (editable)
A4: BLACK = formula (derived from inputs)
A6: INPUTS - EDIT BLUE CELLS TO FLEX ASSUMPTIONS
A7: Starting Revenue ($M) | B7: 88425
A8: Starting EBITDA Margin (%) | B8: 9.9
A9: Cash & Equivalents ($M) | B9: 3633
A10: Existing Debt ($M) | B10: 19363
A11: Market Cap ($M) | B11: 137482
A12: Purchase Premium (%) | B12: 32.4
A13: Leverage at Close (%) | B13: 55
A14: Revenue Growth (%) | B14: 4
A15: Y5 EBITDA Margin (%) | B15: 10.85
A16: Exit Multiple (x) | B16: 12
A17: Interest Rate on Debt (%) | B17: 7
A18: Capex (% of Revenue) | B18: 3
... A20: Hold Period (years) | B20: 5
A22: DERIVED INPUTS (formulas)
A23: Purchase Price ($M) | B23: =B11*(1+B12/100)
A24: Debt at Close ($M) | B24: =B23*B13/100
A25: Sponsor Equity at Close ($M) | B25: =B23-B24
A27: 5-YEAR PROJECTIONS - ALL FORMULAS
A28: Metric ($M) | B28: Year 1 | C28: Year 2 | D28: Year 3 | E28: Year 4 | F28: Year 5
A29: Revenue | B29: =$B$7*(1+$B$14/100) | C29: =B29*(1+$B$14/100) | D29: =C29*(1+$B$14/100) | E29: =D29*(1+$B$14/100) | F29: =E29*(1+$B$14/100)
A30: EBITDA Margin (%) | B30: =$B$8+($B$15-$B$8)*1/5 | C30: =$B$8+($B$15-$B$8)*2/5 | D30: =$B$8+($B$15-$B$8)*3/5 | E30: =$B$8+($B$15-$B$8)*4/5 | F30: =$B$8+($B$15-$B$8)*5/5
A31: EBITDA | B31: =B29*B30/100 | C31: =C29*C30/100 | D31: =D29*D30/100 | E31: =E29*E30/100 | F31: =F29*F30/100
A32: Interest Expense | B32: =$B$24*$B$17/100 | C32: =B36*$B$17/100 | D32: =C36*$B$17/100 | E32: =D36*$B$17/100 | F32: =E36*$B$17/100
A33: Capex | B33: =B29*$B$18/100 | C33: =C29*$B$18/100 | D33: =D29*$B$18/100 | E33: =E29*$B$18/100 | F33: =F29*$B$18/100
A34: Taxes | B34: =MAX(0,(B31-B32)*$B$19/100) | C34: =MAX(0,(C31-C32)*$B$19/100) | D34: =MAX(0,(D31-D32)*$B$19/100) | E34: =MAX(0,(E31-E32)*$B$19/100) | F34: =MAX(0,(F31-F32)*$B$19/100)
A35: Free Cash Flow | B35: =B31-B32-B33-B34 | C35: =C31-C32-C33-C34 | D35: =D31-D32-D33-D34 | E35: =E31-E32-E33-E34 | F35: =F31-F32-F33-F34
A36: Debt Balance (EoY) | B36: =MAX(0,$B$24-MAX(0,B35)) | C36: =MAX(0,B36-MAX(0,C35)) | D36: =MAX(0,C36-MAX(0,D35)) | E36: =MAX(0,D36-MAX(0,E35)) | F36: =MAX(0,E36-MAX(0,F35))
A38: EXIT & RETURNS (formulas)
A39: Exit EBITDA ($M) | B39: =F31
A40: Exit EV ($M) | B40: =B39*$B$16
A41: Net Debt at Exit ($M) | B41: =F36
A42: Exit Equity Value ($M) | B42: =MAX(0,B40-B41)
A43: MOIC | B43: =IFERROR(B42/$B$25,0)
A44: IRR (%) | B44: =IFERROR(((B42/$B$25)^(1/$B$20)-1)*100,0)
A46: Tip: Edit any BLUE input cell. Projections, debt paydown, and returns recalculate live.

Sheet Bull Case
A1: BULL CASE - LIVE LBO MODEL
A3: BLUE = hardcoded input (editable)
A4: BLACK = formula (derived from inputs)
A6: INPUTS - EDIT BLUE CELLS TO FLEX ASSUMPTIONS
A7: Starting Revenue ($M) | B7: 88425
A8: Starting EBITDA Margin (%) | B8: 9.9
A9: Cash & Equivalents ($M) | B9: 3633
A10: Existing Debt ($M) | B10: 19363
A11: Market Cap ($M) | B11: 137482
A12: Purchase Premium (%) | B12: 27.4
A13: Leverage at Close (%) | B13: 55
A14: Revenue Growth (%) | B14: 7
A15: Y5 EBITDA Margin (%) | B15: 12.85
A16: Exit Multiple (x) | B16: 14
A17: Interest Rate on Debt (%) | B17: 7
A18: Capex (% of Revenue) | B18: 3
... A20: Hold Period (years) | B20: 5
A22: DERIVED INPUTS (formulas)
A23: Purchase Price ($M) | B23: =B11*(1+B12/100)
A24: Debt at Close ($M) | B24: =B23*B13/100
A25: Sponsor Equity at Close ($M) | B25: =B23-B24
A27: 5-YEAR PROJECTIONS - ALL FORMULAS
A28: Metric ($M) | B28: Year 1 | C28: Year 2 | D28: Year 3 | E28: Year 4 | F28: Year 5
A29: Revenue | B29: =$B$7*(1+$B$14/100) | C29: =B29*(1+$B$14/100) | D29: =C29*(1+$B$14/100) | E29: =D29*(1+$B$14/100) | F29: =E29*(1+$B$14/100)
A30: EBITDA Margin (%) | B30: =$B$8+($B$15-$B$8)*1/5 | C30: =$B$8+($B$15-$B$8)*2/5 | D30: =$B$8+($B$15-$B$8)*3/5 | E30: =$B$8+($B$15-$B$8)*4/5 | F30: =$B$8+($B$15-$B$8)*5/5
A31: EBITDA | B31: =B29*B30/100 | C31: =C29*C30/100 | D31: =D29*D30/100 | E31: =E29*E30/100 | F31: =F29*F30/100
A32: Interest Expense | B32: =$B$24*$B$17/100 | C32: =B36*$B$17/100 | D32: =C36*$B$17/100 | E32: =D36*$B$17/100 | F32: =E36*$B$17/100
A33: Capex | B33: =B29*$B$18/100 | C33: =C29*$B$18/100 | D33: =D29*$B$18/100 | E33: =E29*$B$18/100 | F33: =F29*$B$18/100
A34: Taxes | B34: =MAX(0,(B31-B32)*$B$19/100) | C34: =MAX(0,(C31-C32)*$B$19/100) | D34: =MAX(0,(D31-D32)*$B$19/100) | E34: =MAX(0,(E31-E32)*$B$19/100) | F34: =MAX(0,(F31-F32)*$B$19/100)
A35: Free Cash Flow | B35: =B31-B32-B33-B34 | C35: =C31-C32-C33-C34 | D35: =D31-D32-D33-D34 | E35: =E31-E32-E33-E34 | F35: =F31-F32-F33-F34
A36: Debt Balance (EoY) | B36: =MAX(0,$B$24-MAX(0,B35)) | C36: =MAX(0,B36-MAX(0,C35)) | D36: =MAX(0,C36-MAX(0,D35)) | E36: =MAX(0,D36-MAX(0,E35)) | F36: =MAX(0,E36-MAX(0,F35))
A38: EXIT & RETURNS (formulas)
A39: Exit EBITDA ($M) | B39: =F31
A40: Exit EV ($M) | B40: =B39*$B$16
A41: Net Debt at Exit ($M) | B41: =F36
A42: Exit Equity Value ($M) | B42: =MAX(0,B40-B41)
A43: MOIC | B43: =IFERROR(B42/$B$25,0)
A44: IRR (%) | B44: =IFERROR(((B42/$B$25)^(1/$B$20)-1)*100,0)
A46: Tip: Edit any BLUE input cell. Projections, debt paydown, and returns recalculate live.

Sheet Bear Case
A1: BEAR CASE - LIVE LBO MODEL
A3: BLUE = hardcoded input (editable)
A4: BLACK = formula (derived from inputs)
A6: INPUTS - EDIT BLUE CELLS TO FLEX ASSUMPTIONS
A7: Starting Revenue ($M) | B7: 88425
A8: Starting EBITDA Margin (%) | B8: 9.9
A9: Cash & Equivalents ($M) | B9: 3633
A10: Existing Debt ($M) | B10: 19363
A11: Market Cap ($M) | B11: 137482
A12: Purchase Premium (%) | B12: 37.4
A13: Leverage at Close (%) | B13: 55
A14: Revenue Growth (%) | B14: 1
A15: Y5 EBITDA Margin (%) | B15: 20
A16: Exit Multiple (x) | B16: 10
A17: Interest Rate on Debt (%) | B17: 7
A18: Capex (% of Revenue) | B18: 3
... A20: Hold Period (years) | B20: 5
A22: DERIVED INPUTS (formulas)
A23: Purchase Price ($M) | B23: =B11*(1+B12/100)
A24: Debt at Close ($M) | B24: =B23*B13/100
A25: Sponsor Equity at Close ($M) | B25: =B23-B24
A27: 5-YEAR PROJECTIONS - ALL FORMULAS
A28: Metric ($M) | B28: Year 1 | C28: Year 2 | D28: Year 3 | E28: Year 4 | F28: Year 5
A29: Revenue | B29: =$B$7*(1+$B$14/100) | C29: =B29*(1+$B$14/100) | D29: =C29*(1+$B$14/100) | E29: =D29*(1+$B$14/100) | F29: =E29*(1+$B$14/100)
A30: EBITDA Margin (%) | B30: =$B$8+($B$15-$B$8)*1/5 | C30: =$B$8+($B$15-$B$8)*2/5 | D30: =$B$8+($B$15-$B$8)*3/5 | E30: =$B$8+($B$15-$B$8)*4/5 | F30: =$B$8+($B$15-$B$8)*5/5
A31: EBITDA | B31: =B29*B30/100 | C31: =C29*C30/100 | D31: =D29*D30/100 | E31: =E29*E30/100 | F31: =F29*F30/100
A32: Interest Expense | B32: =$B$24*$B$17/100 | C32: =B36*$B$17/100 | D32: =C36*$B$17/100 | E32: =D36*$B$17/100 | F32: =E36*$B$17/100
A33: Capex | B33: =B29*$B$18/100 | C33: =C29*$B$18/100 | D33: =D29*$B$18/100 | E33: =E29*$B$18/100 | F33: =F29*$B$18/100
A34: Taxes | B34: =MAX(0,(B31-B32)*$B$19/100) | C34: =MAX(0,(C31-C32)*$B$19/100) | D34: =MAX(0,(D31-D32)*$B$19/100) | E34: =MAX(0,(E31-E32)*$B$19/100) | F34: =MAX(0,(F31-F32)*$B$19/100)
A35: Free Cash Flow | B35: =B31-B32-B33-B34 | C35: =C31-C32-C33-C34 | D35: =D31-D32-D33-D34 | E35: =E31-E32-E33-E34 | F35: =F31-F32-F33-F34
A36: Debt Balance (EoY) | B36: =MAX(0,$B$24-MAX(0,B35)) | C36: =MAX(0,B36-MAX(0,C35)) | D36: =MAX(0,C36-MAX(0,D35)) | E36: =MAX(0,D36-MAX(0,E35)) | F36: =MAX(0,E36-MAX(0,F35))
A38: EXIT & RETURNS (formulas)
A39: Exit EBITDA ($M) | B39: =F31
A40: Exit EV ($M) | B40: =B39*$B$16
A41: Net Debt at Exit ($M) | B41: =F36
A42: Exit Equity Value ($M) | B42: =MAX(0,B40-B41)
A43: MOIC | B43: =IFERROR(B42/$B$25,0)
A44: IRR (%) | B44: =IFERROR(((B42/$B$25)^(1/$B$20)-1)*100,0)
A46: Tip: Edit any BLUE input cell. Projections, debt paydown, and returns recalculate live.

Sheet Sensitivity
A1: SENSITIVITY: BASE-CASE IRR (% by Exit Multiple x Revenue Growth)
B3: 10.0x | C3: 11.0x | D3: 12.0x | E3: 13.0x | F3: 14.0x
A4: Growth 1.0% | B4: -22.2 | C4: -17.1 | D4: -13 | E4: -9.6 | F4: -6.6
A5: Growth 3.0% | B5: -16.3 | C5: -12 | D5: -8.4 | E5: -5.3 | F5: -2.5
A6: Growth 4.0% | B6: -13.8 | C6: -9.7 | D6: -6.3 | E6: -3.3 | F6: -0.6
A7: Growth 5.0% | B7: -11.4 | C7: -7.6 | D7: -4.3 | E7: -1.4 | F7: 1.2
A8: Growth 7.0% | B8: -7.2 | C8: -3.6 | D8: -0.5 | E8: 2.2 | F8: 4.7

Sheet Inputs Reference
A1: Inputs from Diligence Pipeline
A3: Ticker | B3: DELL
A4: Company | B4: Dell Technologies Inc.
A5: Revenue ($M) | B5: 88425
A6: EBITDA ($M) | B6: 8714
A7: EBITDA Margin (%) | B7: 9.9
A8: Free Cash Flow ($M) | B8: 5920
A9: Total Debt ($M) | B9: 19363
A10: Cash ($M) | B10: 3633
A11: Market Cap ($M) | B11: 137482
A12: Current Price | B12: 211.45
A13: P/E | B13: 24.360598
A14: EV/EBITDA | B14: 13.655
A15: Beta | B15: 1.062
